{
  "version": 1,
  "description": "TEMIS site-level EmDash contract for graph terms, people/bylines, menus, publications, and fixture relationships.",
  "mediaPolicy": {
    "canonicalStorage": "emdash-r2",
    "checkedInPublicMedia": "Allowed only for V1 fixtures and deterministic local builds. Production editorial media should be uploaded through EmDash and stored in R2.",
    "requiredMetadata": ["alt", "caption", "license"]
  },
  "bylines": [
    {
      "slug": "temis-editorial-team",
      "displayName": "TEMIS editorial team",
      "bio": "The TEMIS editorial team publishes shared notes, platform updates, and working-group material."
    },
    {
      "slug": "lodewijk-gelauff",
      "displayName": "Lodewijk Gelauff",
      "bio": "Lodewijk Gelauff is a computational social scientist working on democratic innovation. He explores Wikimedia governance, dseliberation, and community decision-making tools."
    },
    {
      "slug": "christophe-henner",
      "displayName": "Christophe Henner",
      "bio": "Christophe Henner is a 20-year Wikimedian, former Chair of Wikimedia France, and former Chair of the Wikimedia Foundation Board of Trustees."
    }
  ],
  "taxonomyTerms": [
    {
      "taxonomy": "category",
      "slug": "essays",
      "label": "Essays",
      "description": "Long-form arguments, reflections, and field notes.",
      "priority": 80,
      "accent": "#006f6a"
    },
    {
      "taxonomy": "category",
      "slug": "tools",
      "label": "Tools",
      "description": "Software and prototypes connected to open knowledge work.",
      "priority": 70,
      "accent": "#1137ff"
    },
    {
      "taxonomy": "category",
      "slug": "publications",
      "label": "Publications",
      "description": "Research papers, reports, and external knowledge objects connected to TEMIS work.",
      "priority": 68,
      "accent": "#8a1f5c"
    },
    {
      "taxonomy": "tag",
      "slug": "open-knowledge",
      "label": "Open knowledge",
      "description": "Questions about public knowledge, commons, and shared infrastructure.",
      "priority": 60,
      "accent": "#4f7f45"
    },
    {
      "taxonomy": "tag",
      "slug": "wikipedia",
      "label": "Wikipedia",
      "description": "Essays and tools about Wikipedia as infrastructure, community, and product.",
      "priority": 58,
      "accent": "#111111"
    },
    {
      "taxonomy": "tag",
      "slug": "wikimedia",
      "label": "Wikimedia",
      "description": "Movement, governance, and shared Wikimedia infrastructure.",
      "priority": 56,
      "accent": "#7a4f00"
    },
    {
      "taxonomy": "tag",
      "slug": "ai",
      "label": "AI",
      "description": "AI-era questions for open knowledge, verification, distribution, and tooling.",
      "priority": 54,
      "accent": "#1137ff"
    },
    {
      "taxonomy": "tag",
      "slug": "knowledge-equity",
      "label": "Knowledge equity",
      "description": "Equity questions about whose knowledge is created, maintained, and visible.",
      "priority": 52,
      "accent": "#8a1f5c"
    },
    {
      "taxonomy": "tag",
      "slug": "movement-strategy",
      "label": "Movement strategy",
      "description": "Strategy, governance, and direction-setting for open knowledge movements.",
      "priority": 50,
      "accent": "#006f6a"
    }
  ],
  "taxonomyAssignments": [
    {
      "collection": "posts",
      "slug": "welcome",
      "taxonomy": "category",
      "termSlug": "essays"
    },
    {
      "collection": "posts",
      "slug": "welcome",
      "taxonomy": "tag",
      "termSlug": "open-knowledge"
    },
    {
      "collection": "posts",
      "slug": "innovating-with-wikimedia-decision-making",
      "taxonomy": "category",
      "termSlug": "essays"
    },
    {
      "collection": "posts",
      "slug": "innovating-with-wikimedia-decision-making",
      "taxonomy": "tag",
      "termSlug": "open-knowledge"
    },
    {
      "collection": "tools",
      "slug": "wiki-polis",
      "taxonomy": "category",
      "termSlug": "tools"
    },
    {
      "collection": "tools",
      "slug": "wiki-polis",
      "taxonomy": "tag",
      "termSlug": "open-knowledge"
    },
    {
      "collection": "tools",
      "slug": "sp42",
      "taxonomy": "category",
      "termSlug": "tools"
    },
    {
      "collection": "tools",
      "slug": "sp42",
      "taxonomy": "tag",
      "termSlug": "wikipedia"
    },
    {
      "collection": "tools",
      "slug": "sp42",
      "taxonomy": "tag",
      "termSlug": "wikimedia"
    },
    {
      "collection": "tools",
      "slug": "sp42",
      "taxonomy": "tag",
      "termSlug": "open-knowledge"
    },
    {
      "collection": "tools",
      "slug": "wiki-economics",
      "taxonomy": "category",
      "termSlug": "tools"
    },
    {
      "collection": "tools",
      "slug": "wiki-economics",
      "taxonomy": "tag",
      "termSlug": "wikipedia"
    },
    {
      "collection": "tools",
      "slug": "wiki-economics",
      "taxonomy": "tag",
      "termSlug": "wikimedia"
    },
    {
      "collection": "tools",
      "slug": "wiki-economics",
      "taxonomy": "tag",
      "termSlug": "open-knowledge"
    },
    {
      "collection": "tools",
      "slug": "wiki-economics",
      "taxonomy": "tag",
      "termSlug": "knowledge-equity"
    },
    {
      "collection": "posts",
      "slug": "wikipedia-at-25-a-wake-up-call",
      "taxonomy": "category",
      "termSlug": "essays"
    },
    {
      "collection": "posts",
      "slug": "wikipedia-at-25-a-wake-up-call",
      "taxonomy": "tag",
      "termSlug": "open-knowledge"
    },
    {
      "collection": "posts",
      "slug": "wikipedia-at-25-a-wake-up-call",
      "taxonomy": "tag",
      "termSlug": "wikipedia"
    },
    {
      "collection": "posts",
      "slug": "wikipedia-at-25-a-wake-up-call",
      "taxonomy": "tag",
      "termSlug": "wikimedia"
    },
    {
      "collection": "posts",
      "slug": "wikipedia-at-25-a-wake-up-call",
      "taxonomy": "tag",
      "termSlug": "ai"
    },
    {
      "collection": "posts",
      "slug": "wikipedia-at-25-a-wake-up-call",
      "taxonomy": "tag",
      "termSlug": "knowledge-equity"
    },
    {
      "collection": "posts",
      "slug": "wikipedia-at-25-a-wake-up-call",
      "taxonomy": "tag",
      "termSlug": "movement-strategy"
    }
  ],
  "contentBylines": [
    {
      "collection": "posts",
      "slug": "welcome",
      "bylineSlug": "temis-editorial-team",
      "roleLabel": "Author"
    },
    {
      "collection": "posts",
      "slug": "innovating-with-wikimedia-decision-making",
      "bylineSlug": "lodewijk-gelauff",
      "roleLabel": "Author"
    },
    {
      "collection": "tools",
      "slug": "wiki-polis",
      "bylineSlug": "lodewijk-gelauff",
      "roleLabel": "Creator"
    },
    {
      "collection": "tools",
      "slug": "sp42",
      "bylineSlug": "christophe-henner",
      "roleLabel": "Creator"
    },
    {
      "collection": "tools",
      "slug": "wiki-economics",
      "bylineSlug": "christophe-henner",
      "roleLabel": "Creator"
    },
    {
      "collection": "posts",
      "slug": "wikipedia-at-25-a-wake-up-call",
      "bylineSlug": "christophe-henner",
      "roleLabel": "Author"
    }
  ],
  "contentDefaults": [
    {
      "collection": "pages",
      "slug": "search",
      "fields": {
        "title": "Search",
        "summary": "Search the published TEMIS static snapshot across essays, tools, publications, people, and pages.",
        "content": [
          {
            "_type": "block",
            "style": "normal",
            "children": [
              {
                "_type": "span",
                "text": "This local search index is generated at build time from published EmDash content: essays, tools, publications, people, and pages."
              }
            ]
          }
        ]
      }
    },
    {
      "collection": "pages",
      "slug": "tools",
      "fields": {
        "title": "Tool index",
        "summary": "Software, prototypes, and research pipelines connected to open knowledge work.",
        "content": [
          {
            "_type": "block",
            "style": "normal",
            "children": [
              {
                "_type": "span",
                "text": "Tools are first-class TEMIS records: they connect authors, articles, repositories, topics, and maintenance signals into the graph."
              }
            ]
          }
        ]
      }
    },
    {
      "collection": "pages",
      "slug": "publications",
      "fields": {
        "title": "Publication index",
        "summary": "Research papers, reports, and other publications connected to TEMIS essays, tools, people, and topics.",
        "content": [
          {
            "_type": "block",
            "style": "normal",
            "children": [
              {
                "_type": "span",
                "text": "Publications are first-class knowledge objects in TEMIS. Editorial posts may summarize or discuss them, tools may implement them, and the graph can connect them to people and topics without treating them as ordinary articles."
              }
            ]
          }
        ]
      }
    },
    {
      "collection": "posts",
      "slug": "welcome",
      "fields": {
        "author_name": "TEMIS editorial team",
        "content_type": "team_note"
      }
    },
    {
      "collection": "posts",
      "slug": "innovating-with-wikimedia-decision-making",
      "fields": {
        "author_name": "Lodewijk Gelauff",
        "content_type": "essay"
      }
    },
    {
      "collection": "posts",
      "slug": "wikipedia-at-25-a-wake-up-call",
      "fields": {
        "author_name": "Christophe Henner",
        "content_type": "essay",
        "source_title": "Meta-Wiki",
        "source_url": "https://meta.wikimedia.org/wiki/User:Schiste/what-now",
        "content_license": "CC BY-SA 4.0",
        "content_license_url": "https://creativecommons.org/licenses/by-sa/4.0/"
      }
    }
  ],
  "menus": [
    {
      "name": "primary",
      "label": "Primary",
      "items": [
        {
          "label": "Essays",
          "url": "/blog/"
        },
        {
          "label": "Topics",
          "url": "/topics/"
        },
        {
          "label": "People",
          "url": "/people/"
        },
        {
          "label": "About",
          "url": "/about/"
        }
      ]
    }
  ]
}
